teclab/__init__.py
teclab/client.py
teclab/server.py
teclab/test.py
teclab/utils.py
teclab/adapter/__init__.py
teclab/adapter/manager.py
teclab/adapter/tcp.py
teclab/middleware/__init__.py
teclab/middleware/access.py
teclab/middleware/checksum.py
teclab/middleware/encrypt.py
teclab/middleware/manager.py
teclab/middleware/pack.py
teclab/plugin/__init__.py
teclab/plugin/client/__init__.py
teclab/plugin/client/manager.py
teclab/plugin/server/__init__.py
teclab/plugin/server/manager.py
teclab/plugin/server/sys.py
teclab-1.0.2.dist-info/METADATA
teclab-1.0.2.dist-info/WHEEL
teclab-1.0.2.dist-info/top_level.txt
teclab-1.0.2.dist-info/RECORD
