Metadata-Version: 2.1
Name: teclab
Version: 1.0.2
Summary: Teclab设备统一控制协议
Home-page: https://gitlab.teclab.org.cn/Teclab/iot-protocol
Author: teclab
Author-email: admin@teclab.org.cn
Classifier: Programming Language :: Python :: 3
Classifier: Operating System :: OS Independent
Requires-Python: >=3.6
